{"stats":{"minecraft:killed_by":{"minecraft:spider":1},"minecraft:custom":{"minecraft:time_since_rest":63689,"minecraft:leave_game":1,"minecraft:damage_dealt":384,"minecraft:crouch_one_cm":45,"minecraft:damage_taken":385,"minecraft:play_time":86391,"minecraft:sprint_one_cm":2751,"minecraft:time_since_death":58076,"minecraft:walk_one_cm":10163,"minecraft:deaths":1,"minecraft:sneak_time":8,"minecraft:total_world_time":86391,"minecraft:mob_kills":1,"minecraft:fly_one_cm":4627,"minecraft:fall_one_cm":3205,"minecraft:jump":78},"minecraft:killed":{"minecraft:zombie":1},"minecraft:mined":{"minecraft:oak_leaves":11}},"DataVersion":2860}